<?xml version="1.0" encoding="utf-8"?>
<LanguageData>

  <!-- Luxandra_PrimalLustDeviant -->
  <Luxandra_PrimalLustDeviant.title>淫慾墮異者</Luxandra_PrimalLustDeviant.title>
  <Luxandra_PrimalLustDeviant.titleShort>墮異者</Luxandra_PrimalLustDeviant.titleShort>
  <Luxandra_PrimalLustDeviant.baseDesc>[PAWN_nameDef]意識清醒，思考也仍然清楚，但[PAWN_possessive]心智已被一股絕對而頑固的原始性慾牢牢攫住。雖然[PAWN_pronoun]表面上仍能正常交談，但在偏執的淫慾驅使下，對一般工作的興趣早已徹底蒸發。</Luxandra_PrimalLustDeviant.baseDesc>

  <!-- Luxandra_CarnalAlphaDeviant -->
  <Luxandra_CarnalAlphaDeviant.title>肉慾阿爾法</Luxandra_CarnalAlphaDeviant.title>
  <Luxandra_CarnalAlphaDeviant.titleShort>阿爾法</Luxandra_CarnalAlphaDeviant.titleShort>
  <Luxandra_CarnalAlphaDeviant.baseDesc>[PAWN_nameDef]意識清醒，思考也仍然清楚，並透過殘酷的肉慾支配，對整個群體維持絕對控制。雖然[PAWN_possessive]心智同樣被原始性慾扭曲，[PAWN_pronoun]卻能將這份慾望導向領導，使群體保持足以操縱攻城武器的協調性，並迫使部下服從。</Luxandra_CarnalAlphaDeviant.baseDesc>

  <!-- Luxandra_DeviantChildhoodFeral -->
  <Luxandra_DeviantChildhoodFeral.title>野性墮異者</Luxandra_DeviantChildhoodFeral.title>
  <Luxandra_DeviantChildhoodFeral.titleShort>野性</Luxandra_DeviantChildhoodFeral.titleShort>
  <Luxandra_DeviantChildhoodFeral.baseDesc>[PAWN_nameDef]在未馴的荒野中長大。由於從未學會社會法律、倫理框架，甚至最基本的道德約束，[PAWN_pronoun]的成長幾乎完全由本能，以及對原始衝動的即時滿足所引導。</Luxandra_DeviantChildhoodFeral.baseDesc>

</LanguageData>